claudestine/__init__.py
claudestine/prompts.py
claudestine-1.0.0.dist-info/METADATA
claudestine-1.0.0.dist-info/WHEEL
claudestine-1.0.0.dist-info/licenses/LICENSE
claudestine-1.0.0.dist-info/RECORD
