Metadata-Version: 2.4
Name: claudestine
Version: 1.0.0
Summary: Reverse-engineered Claude Code agent system prompt generator
Project-URL: Homepage, https://github.com/starbased-co/claudestine
Project-URL: Repository, https://github.com/starbased-co/claudestine
Project-URL: Issues, https://github.com/starbased-co/claudestine/issues
Author-email: starbased <s@starbased.net>
License: MIT
License-File: LICENSE
Keywords: agent,ai,anthropic,claude,llm,prompt
Classifier: Development Status :: 4 - Beta
Classifier: Intended Audience :: Developers
Classifier: License :: OSI Approved :: MIT License
Classifier: Programming Language :: Python :: 3
Classifier: Programming Language :: Python :: 3.12
Classifier: Topic :: Scientific/Engineering :: Artificial Intelligence
Classifier: Topic :: Software Development :: Libraries :: Python Modules
Requires-Python: >=3.12
